unchecked_io-0.1.7.dist-info/METADATA
unchecked_io-0.1.7.dist-info/WHEEL
unchecked_io-0.1.7.dist-info/licenses/LICENSE
unchecked_io/__init__.py
unchecked_io/unchecked_io.cpython-312-x86_64-linux-gnu.so
unchecked_io-0.1.7.dist-info/RECORD
