Metadata-Version: 2.4
Name: unchecked-io
Version: 0.1.7
Classifier: Programming Language :: Rust
Classifier: Programming Language :: Python :: Implementation :: CPython
Classifier: Programming Language :: Python :: Implementation :: PyPy
Classifier: Programming Language :: Python :: 3
Classifier: Programming Language :: Python :: 3.9
Classifier: Programming Language :: Python :: 3.10
Classifier: Programming Language :: Python :: 3.11
Classifier: Programming Language :: Python :: 3.12
Classifier: Programming Language :: Python :: 3.13
Classifier: Topic :: Database
Classifier: Topic :: Scientific/Engineering :: Information Analysis
Classifier: Operating System :: POSIX :: Linux
Classifier: Operating System :: Microsoft :: Windows
Classifier: Operating System :: MacOS :: MacOS X
Requires-Dist: arro3-core>=0.1.0
License-File: LICENSE
Summary: The world's fastest, most dangerous PostgreSQL-to-Arrow loader.
Keywords: rust,postgresql,arrow,etl,fast,copy,database
Author: Billthemaker
License: BSL-1.1
Requires-Python: >=3.9
